{
  "name":"loop_attributes"
  , "id":4294967295
  , "nodes":
  [
    {
      "name":"const::'lambda'()"
      , "id":566208800
      , "clk":"No"
      , "fmax":"480.00"
      , "type":"kernel"
      , "children":
      [
        {
          "name":"const::'lambda'().B0"
          , "id":565527312
          , "af":"480.00"
          , "br":"0"
          , "ci":"0"
          , "fo":"Disabled"
          , "ii":"1"
          , "ll":"1"
          , "lt":"9.000000"
          , "mi":"n/a"
          , "pl":"Yes"
          , "tc":"0"
          , "tn":"1"
          , "type":"bb"
        }
        , {
          "name":"const::'lambda'().B1"
          , "id":565162928
          , "af":"480.00"
          , "br":"0"
          , "ci":"0"
          , "fo":"Disabled"
          , "ii":"n/a"
          , "ll":"1"
          , "lt":"7.000000"
          , "mi":"n/a"
          , "pl":"No"
          , "tc":"0"
          , "tn":"1"
          , "details":
          [
            {
              "type":"text"
              , "text":"Hyper-Optimized loop structure: disabled."
              , "details":
              [
                {
                  "type":"text"
                  , "text":"Hyper-Optimized loop structure is disabled due to loop not pipelined"
                }
              ]
            }
          ]
          , "debug":
          [
            [
              {
                "filename":"/home/alejandror/parallel-bfs/src/parallel_bfs.cpp"
                , "line":107
              }
            ]
          ]
          , "type":"loop"
          , "children":
          [
            {
              "name":"const::'lambda'().B3"
              , "id":565163088
              , "af":"480.00"
              , "br":"0"
              , "ci":"0"
              , "fo":"Enabled"
              , "ii":"1"
              , "ll":"2"
              , "lt":"423.000000"
              , "mi":"1"
              , "pl":"Yes"
              , "tc":"0"
              , "tn":"1"
              , "details":
              [
                {
                  "type":"text"
                  , "text":"Hyper-Optimized loop structure: enabled."
                }
              ]
              , "debug":
              [
                [
                  {
                    "filename":"/home/alejandror/parallel-bfs/src/parallel_bfs.cpp"
                    , "line":114
                  }
                ]
              ]
              , "type":"loop"
              , "children":
              [
                {
                  "name":"const::'lambda'().B4"
                  , "id":565163168
                  , "af":"480.00"
                  , "br":"1"
                  , "ci":"0"
                  , "fo":"Enabled"
                  , "ii":"648"
                  , "ll":"3"
                  , "lt":"663.000000"
                  , "mi":"648"
                  , "pl":"Yes"
                  , "tc":"0"
                  , "tn":"1"
                  , "details":
                  [
                    {
                      "type":"text"
                      , "text":"Hyper-Optimized loop structure: enabled."
                    }
                  ]
                  , "debug":
                  [
                    [
                      {
                        "filename":"/home/alejandror/parallel-bfs/src/parallel_bfs.cpp"
                        , "line":114
                      }
                    ]
                  ]
                  , "type":"loop"
                }
              ]
            }
            , {
              "name":"const::'lambda'().B5"
              , "id":565163248
              , "af":"480.00"
              , "br":"1"
              , "ci":"0"
              , "fo":"Disabled"
              , "ii":"1"
              , "ll":"2"
              , "lt":"1.000000"
              , "mi":"n/a"
              , "pl":"Yes"
              , "tc":"0"
              , "tn":"1"
              , "type":"bb"
            }
            , {
              "name":"const::'lambda'().B2"
              , "id":565163008
              , "af":"480.00"
              , "br":"0"
              , "ci":"0"
              , "fo":"Disabled"
              , "ii":"1"
              , "ll":"2"
              , "lt":"6.000000"
              , "mi":"n/a"
              , "pl":"Yes"
              , "tc":"0"
              , "tn":"1"
              , "type":"bb"
            }
            , {
              "name":"const::'lambda'().B7"
              , "id":565163408
              , "af":"480.00"
              , "br":"1"
              , "ci":"0"
              , "fo":"Enabled"
              , "ii":"1"
              , "ll":"2"
              , "lt":"204.000000"
              , "mi":"1"
              , "pl":"Yes"
              , "tc":"0"
              , "tn":"1"
              , "details":
              [
                {
                  "type":"text"
                  , "text":"Hyper-Optimized loop structure: enabled."
                }
              ]
              , "debug":
              [
                [
                  {
                    "filename":"/home/alejandror/parallel-bfs/src/parallel_bfs.cpp"
                    , "line":126
                  }
                ]
              ]
              , "type":"loop"
            }
            , {
              "name":"const::'lambda'().B6"
              , "id":565163328
              , "af":"480.00"
              , "br":"0"
              , "ci":"0"
              , "fo":"Disabled"
              , "ii":"1"
              , "ll":"2"
              , "lt":"0.000000"
              , "mi":"n/a"
              , "pl":"Yes"
              , "tc":"0"
              , "tn":"1"
              , "type":"bb"
            }
            , {
              "name":"const::'lambda'().B8"
              , "id":565163488
              , "af":"480.00"
              , "br":"1"
              , "ci":"0"
              , "fo":"Disabled"
              , "ii":"218"
              , "ll":"2"
              , "lt":"256.000000"
              , "mi":"1"
              , "pl":"Yes"
              , "tc":"0"
              , "tn":"0"
              , "details":
              [
                {
                  "type":"text"
                  , "text":"Hyper-Optimized loop structure: disabled."
                }
              ]
              , "debug":
              [
                [
                  {
                    "filename":"/home/alejandror/parallel-bfs/src/parallel_bfs.cpp"
                    , "line":135
                  }
                ]
              ]
              , "type":"loop"
            }
          ]
        }
        , {
          "name":"const::'lambda'().B9"
          , "id":565163568
          , "af":"480.00"
          , "br":"1"
          , "ci":"0"
          , "fo":"Disabled"
          , "ii":"1"
          , "ll":"1"
          , "lt":"7.000000"
          , "mi":"n/a"
          , "pl":"Yes"
          , "tc":"0"
          , "tn":"1"
          , "type":"bb"
        }
        , {
          "name":"const::'lambda'().B10"
          , "id":565163648
          , "af":"480.00"
          , "br":"0"
          , "ci":"0"
          , "fo":"Disabled"
          , "ii":"1"
          , "ll":"1"
          , "lt":"1.000000"
          , "mi":"n/a"
          , "pl":"Yes"
          , "tc":"0"
          , "tn":"1"
          , "type":"bb"
        }
      ]
    }
  ]
}
